pkg/__init__.py
pkg/__main__.py
pkg/query.py
pkg/server.py
pkg/tests/__init__.py
pkg/tests/test_query.py
duckdb_server-0.20.0.dist-info/METADATA
duckdb_server-0.20.0.dist-info/WHEEL
duckdb_server-0.20.0.dist-info/entry_points.txt
duckdb_server-0.20.0.dist-info/RECORD
