Metadata-Version: 2.4
Name: duckdb-server
Version: 0.20.0
Summary: A DuckDB server for Mosaic
Project-URL: homepage, https://github.com/uwdata/mosaic
Requires-Python: >=3.10
Requires-Dist: diskcache
Requires-Dist: duckdb>=1.3.1
Requires-Dist: pandas
Requires-Dist: pyarrow
Requires-Dist: socketify
Requires-Dist: ujson
